NaviNIBS_Cobot/.git/COMMIT_EDITMSG
NaviNIBS_Cobot/.git/config
NaviNIBS_Cobot/.git/description
NaviNIBS_Cobot/.git/FETCH_HEAD
NaviNIBS_Cobot/.git/HEAD
NaviNIBS_Cobot/.git/hooks/applypatch-msg.sample
NaviNIBS_Cobot/.git/hooks/commit-msg.sample
NaviNIBS_Cobot/.git/hooks/fsmonitor-watchman.sample
NaviNIBS_Cobot/.git/hooks/post-update.sample
NaviNIBS_Cobot/.git/hooks/pre-applypatch.sample
NaviNIBS_Cobot/.git/hooks/pre-commit.sample
NaviNIBS_Cobot/.git/hooks/pre-merge-commit.sample
NaviNIBS_Cobot/.git/hooks/pre-push.sample
NaviNIBS_Cobot/.git/hooks/pre-rebase.sample
NaviNIBS_Cobot/.git/hooks/pre-receive.sample
NaviNIBS_Cobot/.git/hooks/prepare-commit-msg.sample
NaviNIBS_Cobot/.git/hooks/push-to-checkout.sample
NaviNIBS_Cobot/.git/hooks/sendemail-validate.sample
NaviNIBS_Cobot/.git/hooks/update.sample
NaviNIBS_Cobot/.git/index
NaviNIBS_Cobot/.git/info/exclude
NaviNIBS_Cobot/.git/logs/HEAD
NaviNIBS_Cobot/.git/logs/refs/heads/main
NaviNIBS_Cobot/.git/logs/refs/remotes/origin/HEAD
NaviNIBS_Cobot/.git/logs/refs/remotes/origin/main
NaviNIBS_Cobot/.git/objects/00/8d0adeee5e732da08befc262715ff214439448
NaviNIBS_Cobot/.git/objects/05/b0f02d29d265d82495093ecec756b2bc4f5878
NaviNIBS_Cobot/.git/objects/05/dc8ca2e5c6bb4890983ac960c75f84559f90ac
NaviNIBS_Cobot/.git/objects/06/9ee41ecda2583a04cc229ab9ee0fd54da84f2f
NaviNIBS_Cobot/.git/objects/0d/c2ce56a412b86178aa0e57f9a8a3142c0a5f72
NaviNIBS_Cobot/.git/objects/0d/cf77682271d6089de21512fffb51a50b21fc1f
NaviNIBS_Cobot/.git/objects/0e/7b0475325676c7053366bfb45c8721d99e24b2
NaviNIBS_Cobot/.git/objects/0f/414670e39d5661a45f4ab57b5d3d559de80814
NaviNIBS_Cobot/.git/objects/11/47f75a26e2c324c98df5c0a56463fa3b995e11
NaviNIBS_Cobot/.git/objects/12/20bb86a8c7f2dcff4bd1813868b453caed332e
NaviNIBS_Cobot/.git/objects/12/4cc3f450fee31ad48f86bec08dccd70ef7b06a
NaviNIBS_Cobot/.git/objects/13/905f21c79a23c3dfea8a369450418639abddc2
NaviNIBS_Cobot/.git/objects/15/d3aae864ffd0f0b2d74e5e08751c2bf45ad48c
navinibs_cobot-0.1.6.dist-info/COPYING
navinibs_cobot-0.1.6.dist-info/COPYING.LESSER
navinibs_cobot-0.1.6.dist-info/METADATA
navinibs_cobot-0.1.6.dist-info/WHEEL
navinibs_cobot-0.1.6.dist-info/RECORD
